sconf/__init__.py
sconf/config.py
sconf/container.py
sconf/dumps.py
sconf/registry.py
sconf/types.py
sconf/utils.py
sconf-0.2.5.dist-info/LICENSE
sconf-0.2.5.dist-info/METADATA
sconf-0.2.5.dist-info/WHEEL
sconf-0.2.5.dist-info/top_level.txt
sconf-0.2.5.dist-info/RECORD
