Metadata-Version: 2.1
Name: sconf
Version: 0.2.5
Summary: Simple config supporting CLI modification
Home-page: https://github.com/khanrc/sconf
Author: khanrc
Author-email: khanrc@naver.com
License: MIT
Platform: UNKNOWN
Classifier: Programming Language :: Python :: 3
Classifier: Programming Language :: Python :: 3.6
Classifier: Programming Language :: Python :: 3.7
Classifier: Programming Language :: Python :: 3.8
Classifier: Programming Language :: Python :: 3.9
Requires-Python: >=3.6
Requires-Dist: ruamel.yaml
Requires-Dist: munch
